notebook_cat/__init__.py
notebook_cat/core.py
notebook_cat/main.py
notebook_cat/utils.py
notebook_cat/validation.py
notebook_cat/webui.py
notebook_cat/config/__init__.py
notebook_cat/config/defaults.py
notebook_cat-1.5.0.dist-info/licenses/LICENSE
notebook_cat-1.5.0.dist-info/METADATA
notebook_cat-1.5.0.dist-info/WHEEL
notebook_cat-1.5.0.dist-info/entry_points.txt
notebook_cat-1.5.0.dist-info/top_level.txt
notebook_cat-1.5.0.dist-info/RECORD
